Labs/Lab9/dffe_pos.v

module dffe_pos(
    // CONTROL SIGNALS
    clk,
    en,
    clr,

    // DFFE I/O
    data_in,
    data_out
);
   
    // CONTROL SIGNALS
    input clk, en, clr;
    wire clr;
   
    // DFFE I/O
    input data_in;
    output data_out;

    reg data_out;

    /*  --- POSEDGE WRITE DFFE IMPLEMENTATION -----------------------------  */
    // Intialize data_out to 0
    initial
    begin
        data_out = 1'b0;
    end

    // Set value of data_out on positive edge of the clock or clear
    always @(posedge clk) begin
        // If clear is high, set data_out to 0
        if (clr) begin
            data_out <= 1'b0;
        // If enable is high, set data_out to the value of data_in
        end else if (en) begin
            data_out <= data_in;
        end
    end

endmodule

Labs/Lab9/moore.v


module moore(
    // CONTROL SIGNALS
    clk,
    w,
    out
);
   
    input clk, w;
   
    output out;

    /*  --- MOORE MOD-5 COUNTER IMPLEMENTATION -----------------------------  */
    
    wire [2:0] data_out, Y, next;
    wire y0, y1, y2;
    
    assign Y[0] = ((~w && y0) || (w && ~y0));
    assign Y[1] = ((~w && y1) || (y1 && ~y0) || (w && y0 && ~y1));
    assign Y[2] = ((~w && y2) || (~y0 && y2) || (~y1 && y2) || (w && y0 && y1 && ~y2));

    assign data_out = {y2, y1, y0};

    assign out = (data_out == 3'b100) ? 1'b1 : 1'b0;

    dffe_pos y0_state(
        .clk(clk),
        .en(1'b1),
        .clr((data_out == 3'b100 && w)),
        .data_in(Y[0]),
        .data_out(y0)
    );

    dffe_pos y1_state(
        .clk(clk),
        .en(1'b1),
        .clr((data_out == 3'b100 && w)),
        .data_in(Y[1]),
        .data_out(y1)
    );

    dffe_pos y2_state(
        .clk(clk),
        .en(1'b1),
        .clr((data_out == 3'b100 && w)),
        .data_in(Y[2]),
        .data_out(y2)
    );

endmodule

Labs/Lab9/moore_tb.v
`timescale 1ns / 1ps

module moore_tb;

    // Testbench signals
    reg clk;
    reg w;
    wire out;
    wire [2:0] data_out;
    wire [2:0] Y;  // For monitoring

    // Instantiate the counter module
    moore UUT (
        .clk(clk),
        .w(w),
        .out(out)
    );

    assign data_out = UUT.data_out;
    assign Y = UUT.Y;

    initial begin
        // Initialize signals
        clk = 0;

        // Stimulus: Toggle `w` to see effect on the counter
        forever begin
            #10 clk = ~clk;

        end
    end
    
    // Test procedure
    initial begin
        // Initialize signals
        w = 0;
        #15;

        // Stimulus: Toggle `w` to see effect on the counter
        forever begin
            #10 w = ~w;
        end
    end

    // End simulation after a certain time
    initial begin
        #200; // Run the simulation for 200ns
        $finish;
    end

    // Monitor the outputs and clock
    initial begin
        $monitor("clk = %b, w = %b, Present State = %b, Next State = %b, Output = %b", clk, w, data_out, Y, out);
    end

    initial begin
        $dumpfile("moore.vcd");
        $dumpvars(0, moore_tb);
    end

endmodule

Labs/Lab9/moore.vcd
$date
	Fri Apr 19 04:14:30 2024
$end
$version
	Icarus Verilog
$end
$timescale
	1ps
$end
$scope module moore_tb $end
$var wire 3 ! Y [2:0] $end
$var wire 3 " data_out [2:0] $end
$var wire 1 # out $end
$var reg 1 $ clk $end
$var reg 1 % w $end
$scope module UUT $end
$var wire 1 $ clk $end
$var wire 1 % w $end
$var wire 1 & y2 $end
$var wire 1 ' y1 $end
$var wire 1 ( y0 $end
$var wire 1 # out $end
$var wire 3 ) data_out [2:0] $end
$var wire 3 * Y [2:0] $end
$scope module y0_state $end
$var wire 1 $ clk $end
$var wire 1 + clr $end
$var wire 1 , data_in $end
$var wire 1 - en $end
$var reg 1 ( data_out $end
$upscope $end
$scope module y1_state $end
$var wire 1 $ clk $end
$var wire 1 . clr $end
$var wire 1 / data_in $end
$var wire 1 0 en $end
$var reg 1 ' data_out $end
$upscope $end
$scope module y2_state $end
$var wire 1 $ clk $end
$var wire 1 1 clr $end
$var wire 1 2 data_in $end
$var wire 1 3 en $end
$var reg 1 & data_out $end
$upscope $end
$upscope $end
$upscope $end
$enddefinitions $end
#0
$dumpvars
13
02
01
10
0/
0.
1-
0,
0+
b0 *
b0 )
0(
0'
0&
0%
0$
0#
b0 "
b0 !
$end
#10000
1$
#20000
0$
#25000
1,
b1 !
b1 *
1%
#30000
1/
0,
b10 !
b10 *
b1 "
b1 )
1(
1$
#35000
1,
0/
b1 !
b1 *
0%
#40000
0$
#45000
0,
1/
b10 !
b10 *
1%
#50000
1,
02
1/
b11 !
b11 *
0(
b10 "
b10 )
1'
1$
#55000
0,
b10 !
b10 *
0%
#60000
0$
#65000
1,
b11 !
b11 *
1%
#70000
12
0/
0,
b100 !
b100 *
b11 "
b11 )
1(
1$
#75000
1/
02
1,
b11 !
b11 *
0%
#80000
0$
#85000
0/
12
0,
b100 !
b100 *
1%
#90000
1,
12
1#
b101 !
b101 *
1+
1.
11
0(
0'
b100 "
b100 )
1&
1$
#95000
0,
0#
b100 !
b100 *
0+
0.
01
0%
#100000
0$
#105000
1,
b101 !
b101 *
1+
1.
11
1%
#110000
02
b1 !
b1 *
0+
0.
01
b0 "
b0 )
0&
0#
1$
#115000
0,
b0 !
b0 *
0%
#120000
0$
#125000
1,
b1 !
b1 *
1%
#130000
1/
0,
b10 !
b10 *
b1 "
b1 )
1(
1$
#135000
1,
0/
b1 !
b1 *
0%
#140000
0$
#145000
0,
1/
b10 !
b10 *
1%
#150000
1,
b11 !
b11 *
1'
b10 "
b10 )
0(
1$
#155000
0,
b10 !
b10 *
0%
#160000
0$
#165000
1,
b11 !
b11 *
1%
#170000
12
0/
0,
b100 !
b100 *
b11 "
b11 )
1(
1$
#175000
1/
02
1,
b11 !
b11 *
0%
#180000
0$
#185000
0/
12
0,
b100 !
b100 *
1%
#190000
1,
1#
b101 !
b101 *
1+
1.
11
1&
0'
b100 "
b100 )
0(
1$
#195000
0,
0#
b100 !
b100 *
0+
0.
01
0%
